{
  "Aguascalientes": {
    "confirmed": 80,
    "negatives": 866,
    "suspects": 57,
    "deaths": 2,
    "actives": 15
  },
  "Baja California": {
    "confirmed": 741,
    "negatives": 957,
    "suspects": 685,
    "deaths": 75,
    "actives": 205
  },
  "Baja California Sur": {
    "confirmed": 205,
    "negatives": 604,
    "suspects": 197,
    "deaths": 7,
    "actives": 34
  },
  "Campeche": { "confirmed": 63, "negatives": 145, "suspects": 26, "deaths": 4, "actives": 25 },
  "Coahuila": { "confirmed": 254, "negatives": 1607, "suspects": 609, "deaths": 18, "actives": 51 },
  "Colima": { "confirmed": 11, "negatives": 108, "suspects": 20, "deaths": 2, "actives": 3 },
  "Chiapas": { "confirmed": 68, "negatives": 313, "suspects": 41, "deaths": 3, "actives": 24 },
  "Chihuahua": { "confirmed": 152, "negatives": 334, "suspects": 196, "deaths": 32, "actives": 61 },
  "Ciudad de México": {
    "confirmed": 2710,
    "negatives": 6875,
    "suspects": 1676,
    "deaths": 188,
    "actives": 1030
  },
  "Durango": { "confirmed": 22, "negatives": 337, "suspects": 65, "deaths": 4, "actives": 5 },
  "Guanajuato": {
    "confirmed": 150,
    "negatives": 1990,
    "suspects": 180,
    "deaths": 9,
    "actives": 62
  },
  "Guerrero": { "confirmed": 126, "negatives": 378, "suspects": 83, "deaths": 14, "actives": 46 },
  "Hidalgo": { "confirmed": 92, "negatives": 412, "suspects": 54, "deaths": 15, "actives": 31 },
  "Jalisco": { "confirmed": 216, "negatives": 2936, "suspects": 276, "deaths": 14, "actives": 49 },
  "México": { "confirmed": 901, "negatives": 2198, "suspects": 1193, "deaths": 58, "actives": 277 },
  "Michoacán": { "confirmed": 127, "negatives": 764, "suspects": 155, "deaths": 17, "actives": 60 },
  "Morelos": { "confirmed": 85, "negatives": 349, "suspects": 49, "deaths": 12, "actives": 31 },
  "Nayarit": { "confirmed": 37, "negatives": 196, "suspects": 33, "deaths": 5, "actives": 13 },
  "Nuevo León": {
    "confirmed": 202,
    "negatives": 2311,
    "suspects": 2131,
    "deaths": 6,
    "actives": 55
  },
  "Oaxaca": { "confirmed": 69, "negatives": 402, "suspects": 34, "deaths": 6, "actives": 21 },
  "Puebla": { "confirmed": 360, "negatives": 977, "suspects": 256, "deaths": 45, "actives": 75 },
  "Querétaro": { "confirmed": 85, "negatives": 483, "suspects": 65, "deaths": 6, "actives": 25 },
  "Quintana Roo": {
    "confirmed": 360,
    "negatives": 478,
    "suspects": 150,
    "deaths": 34,
    "actives": 93
  },
  "San Luis Potosí": {
    "confirmed": 66,
    "negatives": 1003,
    "suspects": 81,
    "deaths": 4,
    "actives": 10
  },
  "Sinaloa": { "confirmed": 486, "negatives": 902, "suspects": 179, "deaths": 45, "actives": 191 },
  "Sonora": { "confirmed": 117, "negatives": 611, "suspects": 91, "deaths": 12, "actives": 36 },
  "Tabasco": { "confirmed": 397, "negatives": 608, "suspects": 351, "deaths": 42, "actives": 182 },
  "Tamaulipas": { "confirmed": 134, "negatives": 840, "suspects": 175, "deaths": 5, "actives": 76 },
  "Tlaxcala": { "confirmed": 78, "negatives": 459, "suspects": 69, "deaths": 4, "actives": 24 },
  "Veracruz": { "confirmed": 156, "negatives": 1021, "suspects": 377, "deaths": 12, "actives": 64 },
  "Yucatán": { "confirmed": 191, "negatives": 696, "suspects": 67, "deaths": 10, "actives": 75 },
  "Zacatecas": { "confirmed": 31, "negatives": 330, "suspects": 32, "deaths": 2, "actives": 16 },
  "Total": {
    "confirmed": 8772,
    "negatives": 32490,
    "suspects": 9653,
    "deaths": 712,
    "actives": 2965,
    "tests": 50915
  }
}
